cvsslib/__init__.py
cvsslib/base_enum.py
cvsslib/command.py
cvsslib/example_vectors.py
cvsslib/mixin.py
cvsslib/utils.py
cvsslib/vector.py
cvsslib/contrib/__init__.py
cvsslib/contrib/django_model.py
cvsslib/cvss2/__init__.py
cvsslib/cvss2/calculations.py
cvsslib/cvss2/enums.py
cvsslib/cvss3/__init__.py
cvsslib/cvss3/calculations.py
cvsslib/cvss3/enums.py
cvsslib-0.6.0.dist-info/METADATA
cvsslib-0.6.0.dist-info/RECORD
cvsslib-0.6.0.dist-info/WHEEL
cvsslib-0.6.0.dist-info/entry_points.txt
cvsslib-0.6.0.dist-info/top_level.txt
