Metadata-Version: 1.2
Name: cvsslib
Version: 0.6.0
Summary: CVSS 2/3 utilities
Home-page: https://github.com/ctxis/cvsslib
Author: Tom
Author-email: tom.forbes@contextis.co.uk
License: GPL
Platform: UNKNOWN
Classifier: Framework :: Django
Classifier: Intended Audience :: Developers
Classifier: Programming Language :: Python
Classifier: Programming Language :: Python :: 3
Classifier: Programming Language :: Python :: 3.2
Classifier: Programming Language :: Python :: 3.3
Classifier: Programming Language :: Python :: 3.4
Classifier: Programming Language :: Python :: 3.5
Requires-Python: >=3.5
